swagger_client/__init__.py
swagger_client/api_client.py
swagger_client/configuration.py
swagger_client/rest.py
swagger_client/api/__init__.py
swagger_client/api/analytics_api.py
swagger_client/api/api_keys_api.py
swagger_client/api/automations_api.py
swagger_client/api/bots_api.py
swagger_client/api/bulk_actions_api.py
swagger_client/api/channel_id_integration_api.py
swagger_client/api/contact_list_contacts_api.py
swagger_client/api/contact_lists_api.py
swagger_client/api/conversations_api.py
swagger_client/api/customers_api.py
swagger_client/api/data_api.py
swagger_client/api/event_endpoints_api.py
swagger_client/api/group_members_api.py
swagger_client/api/groups_api.py
swagger_client/api/instant_app_schemas_api.py
swagger_client/api/instant_apps_api.py
swagger_client/api/integrations_api.py
swagger_client/api/maps_api.py
swagger_client/api/messages_api.py
swagger_client/api/org_channels_api.py
swagger_client/api/org_settings_api.py
swagger_client/api/orgs_api.py
swagger_client/api/pool_channels_api.py
swagger_client/api/pools_api.py
swagger_client/api/pounces_api.py
swagger_client/api/presence_api.py
swagger_client/api/scheduled_actions_api.py
swagger_client/api/smart_links_api.py
swagger_client/api/tag_groups_api.py
swagger_client/api/tags_api.py
swagger_client/api/team_members_api.py
swagger_client/api/uploads_api.py
swagger_client/models/__init__.py
swagger_client/models/add_automation_model.py
swagger_client/models/add_bulk_action_fulfillment_model.py
swagger_client/models/add_bulk_action_model.py
swagger_client/models/add_bulk_action_variant_model.py
swagger_client/models/add_conversation_request_model.py
swagger_client/models/add_customer_model.py
swagger_client/models/add_identity_team_member_request_model.py
swagger_client/models/add_or_update_automation_fulfillment_model.py
swagger_client/models/add_or_update_smart_link_fulfillment_model.py
swagger_client/models/add_or_update_smart_link_model.py
swagger_client/models/add_pool_channel_request_model.py
prompt_python_sdk-0.0.1.dist-info/METADATA
prompt_python_sdk-0.0.1.dist-info/WHEEL
prompt_python_sdk-0.0.1.dist-info/top_level.txt
prompt_python_sdk-0.0.1.dist-info/RECORD
