Metadata-Version: 2.1
Name: prompt-python-sdk
Version: 0.0.1
Summary: Prompt.io APIs
Home-page: 
Author-email: 
Project-URL: Homepage, https://github.com/frontrunnerapp/prompt-python-sdk
Keywords: Swagger,Prompt.io APIs
Classifier: Programming Language :: Python :: 3
Classifier: License :: OSI Approved :: MIT License
Classifier: Operating System :: OS Independent
Requires-Python: >=3.8
Requires-Dist: urllib3 (>=1.15)
Requires-Dist: six (>=1.10)
Requires-Dist: certifi
Requires-Dist: python-dateutil
